LICENSE.txt
README.rst
setup.py
autofree/__init__.py
autofree.egg-info/PKG-INFO
autofree.egg-info/SOURCES.txt
autofree.egg-info/dependency_links.txt
autofree.egg-info/top_level.txt